makersign/__init__.py
makersign/led_sign.py
makersign-0.1.dist-info/LICENSE
makersign-0.1.dist-info/METADATA
makersign-0.1.dist-info/WHEEL
makersign-0.1.dist-info/top_level.txt
makersign-0.1.dist-info/RECORD
